impedance/__init__.py
impedance/preprocessing.py
impedance/validation.py
impedance/visualization.py
impedance/models/__init__.py
impedance/models/circuits/__init__.py
impedance/models/circuits/circuits.py
impedance/models/circuits/elements.py
impedance/models/circuits/fitting.py
impedance/tests/__init__.py
impedance/tests/test_circuit_elements.py
impedance/tests/test_circuits.py
impedance/tests/test_fitting.py
impedance/tests/test_model_io.py
impedance/tests/test_preprocessing.py
impedance/tests/test_validation.py
impedance/tests/test_visualization.py
impedance-1.7.1.dist-info/LICENSE
impedance-1.7.1.dist-info/METADATA
impedance-1.7.1.dist-info/WHEEL
impedance-1.7.1.dist-info/top_level.txt
impedance-1.7.1.dist-info/RECORD
