Metadata-Version: 2.1
Name: impedance
Version: 1.7.1
Summary: A package for analyzing electrochemical impedance data
Home-page: https://impedancepy.readthedocs.io/en/latest/
Author: impedance.py developers
Author-email: matt.murbach@gmail.com
Classifier: Programming Language :: Python :: 3
Classifier: License :: OSI Approved :: MIT License
Classifier: Operating System :: OS Independent
Requires-Python: ~=3.7
License-File: LICENSE
